stdmathlib/__init__.py
stdmathlib/algebra.py
stdmathlib/combinatorics.py
stdmathlib/graph.py
stdmathlib/integrals.py
stdmathlib/ode.py
stdmathlib/pde.py
stdmathlib-0.1.10.dist-info/METADATA
stdmathlib-0.1.10.dist-info/WHEEL
stdmathlib-0.1.10.dist-info/top_level.txt
stdmathlib-0.1.10.dist-info/RECORD
