Metadata-Version: 2.1
Name: stdmathlib
Version: 0.1.10
Summary: A library to simplify mathematical computations.
Author-email: AstroKepler <nicholasbrislane1@gmail.com>
Project-URL: Homepage, https://github.com/astrokepler/stdmathlib
Classifier: Programming Language :: Python :: 3
Classifier: License :: OSI Approved :: MIT License
Classifier: Operating System :: OS Independent
Requires-Python: >=3.12
Requires-Dist: sympy>=1.0
Requires-Dist: numpy>=1.18.0
Requires-Dist: matplotlib>=3.0.0
Requires-Dist: scipy>=1.4.0
